biolib/VERSION
biolib/__init__.py
biolib/blast_parser.py
biolib/bootstrap.py
biolib/checksum.py
biolib/common.py
biolib/exceptions.py
biolib/genome_tk.py
biolib/genomic_signature.py
biolib/logger.py
biolib/newick.py
biolib/parallel.py
biolib/pca.py
biolib/seq_io.py
biolib/seq_tk.py
biolib/taxonomy.py
biolib/external/__init__.py
biolib/external/blast.py
biolib/external/diamond.py
biolib/external/execute.py
biolib/external/fastani.py
biolib/external/fasttree.py
biolib/external/hmmer.py
biolib/external/mafft.py
biolib/external/mash.py
biolib/external/muscle.py
biolib/external/prodigal.py
biolib/external/raxml.py
biolib/misc/__init__.py
biolib/misc/custom_help_formatter.py
biolib/misc/time_keeper.py
biolib/plots/__init__.py
biolib/plots/abstract_plot.py
biolib/plots/box_whisker.py
biolib/plots/color_brewer.py
biolib/plots/density.py
biolib/plots/histogram.py
biolib/plots/krona.py
biolib/plots/pie_chart.py
biolib/plots/scatter.py
biolib/plots/scatter2.py
biolib-0.1.9.dist-info/LICENSE
biolib-0.1.9.dist-info/METADATA
biolib-0.1.9.dist-info/WHEEL
biolib-0.1.9.dist-info/top_level.txt
biolib-0.1.9.dist-info/RECORD
